odoo/addons/mail_multicompany/README.rst
odoo/addons/mail_multicompany/__init__.py
odoo/addons/mail_multicompany/__manifest__.py
odoo/addons/mail_multicompany/i18n/es.po
odoo/addons/mail_multicompany/i18n/it.po
odoo/addons/mail_multicompany/i18n/mail_multicompany.pot
odoo/addons/mail_multicompany/models/__init__.py
odoo/addons/mail_multicompany/models/ir_mail_server.py
odoo/addons/mail_multicompany/models/mail_message.py
odoo/addons/mail_multicompany/readme/CONFIGURE.md
odoo/addons/mail_multicompany/readme/CONTRIBUTORS.md
odoo/addons/mail_multicompany/readme/DESCRIPTION.md
odoo/addons/mail_multicompany/readme/USAGE.md
odoo/addons/mail_multicompany/security/mail_security.xml
odoo/addons/mail_multicompany/static/description/icon.png
odoo/addons/mail_multicompany/static/description/index.html
odoo/addons/mail_multicompany/tests/__init__.py
odoo/addons/mail_multicompany/tests/test_mail_multicompany.py
odoo/addons/mail_multicompany/views/ir_mail_server_view.xml
odoo_addon_mail_multicompany-18.0.1.0.0.2.dist-info/METADATA
odoo_addon_mail_multicompany-18.0.1.0.0.2.dist-info/WHEEL
odoo_addon_mail_multicompany-18.0.1.0.0.2.dist-info/top_level.txt
odoo_addon_mail_multicompany-18.0.1.0.0.2.dist-info/RECORD
