Metadata-Version: 2.1
Name: odoo-addon-mail_multicompany
Version: 18.0.1.0.0.2
Requires-Python: >=3.10
Requires-Dist: odoo==18.0.*
Summary: Email Gateway Multi company
Home-page: https://github.com/OCA/multi-company
License: AGPL-3
Author: Odoo Community Association (OCA), Comunitea
Author-email: support@odoo-community.org
Classifier: Programming Language :: Python
Classifier: Framework :: Odoo
Classifier: Framework :: Odoo :: 18.0
Classifier: License :: OSI Approved :: GNU Affero General Public License v3
